IndieEngine/__init__.py
IndieEngine/app.py
IndieEngine/button.py
IndieEngine/character_controller.py
IndieEngine/colour.py
IndieEngine/files.py
IndieEngine/font.py
IndieEngine/gameobject.py
IndieEngine/image.py
IndieEngine/input_feild.py
IndieEngine/inputs.py
IndieEngine/panel.py
IndieEngine/physics.py
IndieEngine/sound_manager.py
IndieEngine/spritesheet.py
IndieEngine/spritestrip_animation.py
IndieEngine/text.py
IndieEngine/tilemap.py
IndieEngine/transform.py
indie_engine-1.0.0.dist-info/LICENSE
indie_engine-1.0.0.dist-info/METADATA
indie_engine-1.0.0.dist-info/WHEEL
indie_engine-1.0.0.dist-info/top_level.txt
indie_engine-1.0.0.dist-info/RECORD
