Metadata-Version: 2.1
Name: indie-engine
Version: 1.0.0
Summary: Pre-written classes for pygame
Home-page: UNKNOWN
Author: Sujal Choudhari
Author-email: sjlchoudhari@gmail.com
License: UNKNOWN
Platform: UNKNOWN
Classifier: Programming Language :: Python :: 3
Classifier: License :: OSI Approved :: MIT License
Classifier: Operating System :: OS Independent
Requires-Python: >=3.7
